dataset_loaders/__init__.py
dataset_loaders/dataset_loader.py
dataset_loaders/hatexplain.py
dataset_loaders/healthfc.py
dataset_loaders/movie_reviews.py
evaluators/AUPRC.py
evaluators/FAD.py
evaluators/IOU.py
evaluators/__init__.py
evaluators/complexity.py
evaluators/faithfulness_auc.py
evaluators/monotonicity.py
evaluators/sensitivity.py
evaluators/softcomprehensiveness.py
evaluators/softsufficiency.py
evaluators/sparseness.py
explainers/__init__.py
explainers/baseexplainer.py
explainers/deeplift.py
explainers/explanation.py
explainers/gradientxinput.py
explainers/guidedbackprop.py
explainers/integratedgradient.py
explainers/lime.py
explainers/shap.py
explainers/shapiq.py
BenchNLP-0.1.0.dist-info/METADATA
BenchNLP-0.1.0.dist-info/WHEEL
BenchNLP-0.1.0.dist-info/entry_points.txt
BenchNLP-0.1.0.dist-info/top_level.txt
BenchNLP-0.1.0.dist-info/RECORD
