Metadata-Version: 2.2
Name: BenchNLP
Version: 0.1.0
Summary: NLP Explainability Benchmarking Framework
Author: Your Name
Requires-Dist: torch
Requires-Dist: transformers
Requires-Dist: captum
Requires-Dist: scikit-learn
Requires-Dist: matplotlib
Requires-Dist: datasets
Requires-Dist: typing
Requires-Dist: copy
Requires-Dist: typing
Requires-Dist: numpy
Requires-Dist: pandas
Requires-Dist: seaborn
Dynamic: author
Dynamic: requires-dist
Dynamic: summary
